ignoro-1.2.2.dist-info/METADATA
ignoro-1.2.2.dist-info/WHEEL
ignoro-1.2.2.dist-info/entry_points.txt
ignoro-1.2.2.dist-info/licenses/LICENSE
ignoro/__init__.py
ignoro/api.py
ignoro/cli.py
ignoro/exceptions.py
ignoro-1.2.2.dist-info/RECORD
