Metadata-Version: 2.1
Name: ignoro
Version: 1.2.2
Summary: A CLI for creating and modifying .gitignore files based on templates from gitignore.io
Keywords: gitignore,gitignore.io,cli,python,typer
Author-Email: solbero <njosol@pm.me>
Maintainer-Email: solbero <njosol@pm.me>
License: MIT
Classifier: Development Status :: 5 - Production/Stable
Classifier: Environment :: Console
Classifier: Intended Audience :: Developers
Classifier: License :: OSI Approved :: MIT License
Classifier: Natural Language :: English
Classifier: Operating System :: OS Independent
Classifier: Programming Language :: Python :: 3
Classifier: Programming Language :: Python :: 3.10
Classifier: Programming Language :: Python :: 3.11
Classifier: Programming Language :: Python :: 3.12
Classifier: Topic :: Utilities
Project-URL: Repository, https://github.com/solbero/ignoro
Project-URL: Changelog, https://github.com/solbero/ignoro/blob/main/CHANGELOG.md
Requires-Python: >=3.10
Requires-Dist: requests>=2.31.0
Requires-Dist: typer[all]>=0.9.0
